onetrick.py
setup.py
onetrick.egg-info/PKG-INFO
onetrick.egg-info/SOURCES.txt
onetrick.egg-info/dependency_links.txt
onetrick.egg-info/top_level.txt
test/testmodule.py