Metadata-Version: 2.1
Name: onetrick
Version: 2.1.1
Summary: one module, one call
Home-page: UNKNOWN
Author: Perzan
Author-email: PerzanDevelopment@gmail.com
License: UNKNOWN
Platform: UNKNOWN
Requires-Python: ~=3.5
